lib/audio_tools_mcp_server.py
assembly_ai_mcp-0.1.0.dist-info/METADATA
assembly_ai_mcp-0.1.0.dist-info/WHEEL
assembly_ai_mcp-0.1.0.dist-info/top_level.txt
assembly_ai_mcp-0.1.0.dist-info/RECORD
