Metadata-Version: 2.4
Name: assembly-ai-mcp
Version: 0.1.0
Summary: Add your description here
Requires-Python: >=3.13
Requires-Dist: assemblyai>=0.38.0
Requires-Dist: fast-agent-mcp>=0.2.17
